ivvv/__init__.py
ivvv/_version.py
ivvv/img_prep.py
ivvv/volume.py
ivvv/static/extension.js
ivvv/static/index.js
ivvv/static/index.js.map
ivvv-0.1.0.data/data/etc/jupyter/nbconfig/notebook.d/ivvv.json
ivvv-0.1.0.data/data/share/jupyter/nbextensions/ivvv/extension.js
ivvv-0.1.0.data/data/share/jupyter/nbextensions/ivvv/index.js
ivvv-0.1.0.data/data/share/jupyter/nbextensions/ivvv/index.js.map
ivvv-0.1.0.dist-info/DESCRIPTION.rst
ivvv-0.1.0.dist-info/METADATA
ivvv-0.1.0.dist-info/RECORD
ivvv-0.1.0.dist-info/WHEEL
ivvv-0.1.0.dist-info/metadata.json
ivvv-0.1.0.dist-info/top_level.txt
test/__init__.py
test/test_volume.py
